LICENSE
MANIFEST.in
README.rst
setup.py
django_lazyloader.egg-info/PKG-INFO
django_lazyloader.egg-info/SOURCES.txt
django_lazyloader.egg-info/dependency_links.txt
django_lazyloader.egg-info/requires.txt
django_lazyloader.egg-info/top_level.txt
lazyloader/__init__.py
lazyloader/models.py
lazyloader/urls.py
lazyloader/views.py
lazyloader/fixtures/lazyloader_initial.json
lazyloader/static/lazyloader/css/demo.css
lazyloader/static/lazyloader/js/demo.js
lazyloader/static/lazyloader/js/jquery-1.11.1.min.js
lazyloader/templates/lazyloader/demo.html
lazyloader/templates/lazyloader/demo_html.html